laspec/__init__.py
laspec/analysis.py
laspec/artifact.py
laspec/bh.py
laspec/binning.py
laspec/ccf.py
laspec/ccf2.py
laspec/convolution.py
laspec/core.py
laspec/fof.py
laspec/gauss.py
laspec/helper.py
laspec/interpolate.py
laspec/lamost.py
laspec/lamost_kits.py
laspec/light_curve.py
laspec/line_index.py
laspec/lm.py
laspec/mpl.py
laspec/mrs.py
laspec/ndpe.py
laspec/neural_network.py
laspec/nn.py
laspec/normalization.py
laspec/optimize.py
laspec/publish.py
laspec/qconv.py
laspec/read_spectrum.py
laspec/rvzp.py
laspec/scratch.py
laspec/slam.py
laspec/slam_model.py
laspec/slamconv.py
laspec/slamplus.py
laspec/snstat.py
laspec/spec.py
laspec/ssh.py
laspec/stilts.py
laspec/untitled1.py
laspec/utils.py
laspec/wavelength.py
laspec/data/lamost/l9waveBR.dump
laspec/data/lamost/m9waveBR.dump
laspec/extern/__init__.py
laspec/extern/interpolate.py
laspec/extern/polynomial.py
laspec/old/__init__.py
laspec/old/echelle.py
laspec/old/spec_quick_view.py
laspec-2023.819.0.dist-info/LICENSE
laspec-2023.819.0.dist-info/METADATA
laspec-2023.819.0.dist-info/WHEEL
laspec-2023.819.0.dist-info/top_level.txt
laspec-2023.819.0.dist-info/RECORD
